anon_testo/__init__.py
anon_testo/anon_testo.py
anon_testo/it_fiscal_code_recognizer.py
anon_testo/it_vat_code.py
anon_testo/stop_words.py
anon_testo-0.7.0.dist-info/LICENSE.md
anon_testo-0.7.0.dist-info/METADATA
anon_testo-0.7.0.dist-info/WHEEL
anon_testo-0.7.0.dist-info/top_level.txt
anon_testo-0.7.0.dist-info/RECORD
